{
    "error": false,
    "version": "thirteen",
    "filename": "Spark-13.1-Official-davinci-20221011-gapps.zip",
    "datetime": 1665471465,
    "size": 2052177822,
    "url": "https://sourceforge.net/projects/sparkosofficial/files/davinci/Spark-13.1-Official-davinci-20221011-gapps.zip",
    "github_releases_url": "GITHUB_RELEASES_PLACEHOLDER",
    "filehash": "971fc8c774471387ed555a3f5a025644",
    "id": "971fc8c774471387ed555a3f5a025644",
    "maintainers": [
        {
            "main_maintainer": false,
            "github_username": "spkal01",
            "name": "spkal01"
        }
    ],
    "donate_url": "https://PayPal.me/spyroskal",
    "website_url": "https://spark-os.live/",
    "news_url": "https://t.me/SparkOSChannel",
    "forum_url": ""
}